inmanta_plugins/yaml/__init__.py
inmanta_plugins/yaml/setup.cfg
inmanta_plugins/yaml/model/_init.cf
inmanta_module_yaml-1.0.0.dist-info/METADATA
inmanta_module_yaml-1.0.0.dist-info/WHEEL
inmanta_module_yaml-1.0.0.dist-info/top_level.txt
inmanta_module_yaml-1.0.0.dist-info/RECORD
