Metadata-Version: 2.1
Name: inmanta-module-yaml
Version: 1.0.0
Summary: A module to help with handling yaml files
License: ASL 2.0
Requires-Dist: inmanta-module-std
Requires-Dist: PyYAML
